blockchainpack/__init__.py
blockchainpack/block.py
blockchainpack-0.0.1.dist-info/METADATA
blockchainpack-0.0.1.dist-info/WHEEL
blockchainpack-0.0.1.dist-info/top_level.txt
blockchainpack-0.0.1.dist-info/RECORD
