Metadata-Version: 2.1
Name: blockchainpack
Version: 0.0.1
Summary: A module to help you make a blockchain
Home-page: UNKNOWN
Author: Advaith S
Author-email: <popular9adu@gmail.com>
License: UNKNOWN
Keywords: python,blockchain,python3,cryptocurrency
Platform: UNKNOWN
Classifier: Development Status :: 1 - Planning
Classifier: Intended Audience :: Developers
Classifier: Programming Language :: Python :: 3
Classifier: Operating System :: Unix
Classifier: Operating System :: MacOS :: MacOS X
Classifier: Operating System :: Microsoft :: Windows
